{"id":"Piramide","autor":"Carla Lancelotti","lugar":"Sudan","coordenadas":{"lat":12.8928,"lng":29.998197},"render":{"id":"Piramide","mesh":"piramide/mesh.obj","texture":["piramide/tex_0.jpg"],"rotaciones":[{"r0":-0.6932489275932312},{"r1":0.08118511736392975},{"r2":0.13002026081085205},{"r3":0.7042101621627808}], "metro": -1},"extra":[{"type":"text","data":"Piramide"},{"type":"image","data":"http://img.planospara.com/plano-general-de-qenqo-en-sitios-arqueologicos-historia-30992.gif"},{"type":"pdf","data":"data/wpbr.pdf"},{"type":"text","data":"Hola que tal, soy subnormal"},{"type":"text","data":"esto es otro parrafo"},{"type":"youtube","data":"https://www.youtube.com/embed/6W3R5ItkREk"}]}